ipybertin/__init__.py
ipybertin/_frontend.py
ipybertin/_version.py
ipybertin/bertin.py
ipybertin/labextension/build_log.json
ipybertin/labextension/package.json
ipybertin/labextension/static/lib_index_js.328b0d56c69d160590d3.js
ipybertin/labextension/static/lib_index_js.328b0d56c69d160590d3.js.map
ipybertin/labextension/static/lib_index_js.438acad6eb7fb8979cda.js
ipybertin/labextension/static/lib_index_js.438acad6eb7fb8979cda.js.map
ipybertin/labextension/static/lib_index_js.61d7e52dd6e4f7df66f7.js
ipybertin/labextension/static/lib_index_js.61d7e52dd6e4f7df66f7.js.map
ipybertin/labextension/static/lib_index_js.ad2a16c45648503a240d.js
ipybertin/labextension/static/lib_index_js.ad2a16c45648503a240d.js.map
ipybertin/labextension/static/lib_index_js.e74b6d44ff38e7098dee.js
ipybertin/labextension/static/lib_index_js.e74b6d44ff38e7098dee.js.map
ipybertin/labextension/static/lib_plugin_js.0be5d8fa64675699d763.js
ipybertin/labextension/static/lib_plugin_js.0be5d8fa64675699d763.js.map
ipybertin/labextension/static/lib_plugin_js.a2439315215fa0ac4fb4.js
ipybertin/labextension/static/lib_plugin_js.a2439315215fa0ac4fb4.js.map
ipybertin/labextension/static/lib_plugin_js.a9e22bd63b065bdf5236.js
ipybertin/labextension/static/lib_plugin_js.a9e22bd63b065bdf5236.js.map
ipybertin/labextension/static/lib_plugin_js.b429a7b366fe2da9e88e.js
ipybertin/labextension/static/lib_plugin_js.b429a7b366fe2da9e88e.js.map
ipybertin/labextension/static/lib_plugin_js.f3b43594da2edc2154e3.js
ipybertin/labextension/static/lib_plugin_js.f3b43594da2edc2154e3.js.map
ipybertin/labextension/static/node_modules_d3-array_src_merge_js-node_modules_d3-array_src_range_js.5669144fd6842d3a41b1.js
ipybertin/labextension/static/node_modules_d3-array_src_merge_js-node_modules_d3-array_src_range_js.5669144fd6842d3a41b1.js.map
ipybertin/labextension/static/remoteEntry.261c7f0149302e5a946c.js.map
ipybertin/labextension/static/remoteEntry.2f213b6bebecc31474b5.js.map
ipybertin-0.2.0.dist-info/LICENSE.txt
ipybertin-0.2.0.dist-info/METADATA
ipybertin-0.2.0.dist-info/WHEEL
ipybertin-0.2.0.dist-info/top_level.txt
ipybertin-0.2.0.dist-info/RECORD
